{"version":1,"kind":"Article","sha256":"be69bb7768f501c280793612ef17aa80b184033c4c55bb3a075d05cf83f72221","slug":"blog.2019.2019-10-13-rust-jupyter-governance","location":"/blog/2019/2019-10-13-rust-jupyter-governance.md","dependencies":[],"frontmatter":{"title":"What would Rust-style governance look like in Jupyter?","tags":["governance"],"date":"2019-10-13","content_includes_title":false,"authors":[{"id":"chris","nameParsed":{"literal":"Chris Holdgraf","given":"Chris","family":"Holdgraf"},"name":"Chris Holdgraf","orcid":"0000-0002-2391-0678","affiliations":["affiliations-myst-generated-uid-0","affiliations-myst-generated-uid-1"],"twitter":"choldgraf","github":"choldgraf","url":"https://chrisholdgraf.com"}],"github":"https://github.com/choldgraf/choldgraf.github.io","affiliations":[{"name":"2i2c","url":"https://2i2c.org","id":"affiliations-myst-generated-uid-0"},{"name":"Project Jupyter","url":"https://jupyter.org","id":"affiliations-myst-generated-uid-1"}],"abbreviations":{"LF":"The Linux Foundation","JF":"The Jupyter Foundation","JEC":"Jupyter Executive Council","JFB":"The Jupyter Foundation Board","SSC":"Software Steering Council"},"numbering":{"title":{"offset":2}},"edit_url":"https://github.com/choldgraf/choldgraf.github.io/blob/main/blog/2019/2019-10-13-rust-jupyter-governance.md","exports":[{"format":"md","filename":"2019-10-13-rust-jupyter-governance.md","url":"/build/2019-10-13-rust-jupy-e50daa7afa7c0e02240a8f1cca7214b8.md"}]},"mdast":{"type":"root","children":[{"type":"block","children":[{"type":"paragraph","position":{"start":{"line":12,"column":1},"end":{"line":14,"column":1}},"children":[{"type":"text","value":"As I’ve written about before, I ","position":{"start":{"line":12,"column":1},"end":{"line":12,"column":1}},"key":"njWtd4AqY4"},{"type":"link","url":"https://chrisholdgraf.com/rust-governance","position":{"start":{"line":12,"column":1},"end":{"line":12,"column":1}},"children":[{"type":"text","value":"like Rust’s governance structure","position":{"start":{"line":12,"column":1},"end":{"line":12,"column":1}},"key":"PizcR0R1jp"}],"urlSource":"https://chrisholdgraf.com/rust-governance","key":"uI0NVhVgkM"},{"type":"text","value":".\nI mean, who can’t get behind a community that\n","position":{"start":{"line":12,"column":1},"end":{"line":12,"column":1}},"key":"hPJSIzUt1i"},{"type":"link","url":"https://www.rust-lang.org/governance","position":{"start":{"line":12,"column":1},"end":{"line":12,"column":1}},"children":[{"type":"text","value":"lists governance as a top-level page on its website","position":{"start":{"line":12,"column":1},"end":{"line":12,"column":1}},"key":"S0cMPnJC8A"}],"urlSource":"https://www.rust-lang.org/governance","key":"QnoFQfEKhM"},{"type":"text","value":"?","position":{"start":{"line":12,"column":1},"end":{"line":12,"column":1}},"key":"ycDe2Dq3W1"}],"key":"DKh5g03EnJ"},{"type":"paragraph","position":{"start":{"line":16,"column":1},"end":{"line":20,"column":1}},"children":[{"type":"text","value":"Jupyter is currently in the middle of\n","position":{"start":{"line":16,"column":1},"end":{"line":16,"column":1}},"key":"AIuqP3ZoAs"},{"type":"link","url":"https://discourse.jupyter.org/t/governance-office-hours-meeting-minutes/1480/26","position":{"start":{"line":16,"column":1},"end":{"line":16,"column":1}},"children":[{"type":"text","value":"figuring out the next phase of its governance structure","position":{"start":{"line":16,"column":1},"end":{"line":16,"column":1}},"key":"AI3CsQGcrj"}],"urlSource":"https://discourse.jupyter.org/t/governance-office-hours-meeting-minutes/1480/26","key":"DnPXluLEw8"},{"type":"text","value":",\nand so I have been thinking about\nwhat this might look like. This post is a quick thought-experiment to explore what it’d mean\nto port over Rust’s governance directly into the Jupyter community.","position":{"start":{"line":16,"column":1},"end":{"line":16,"column":1}},"key":"InKDp3TMwb"}],"key":"UyoAnLRQyk"},{"type":"paragraph","position":{"start":{"line":22,"column":1},"end":{"line":24,"column":1}},"children":[{"type":"emphasis","position":{"start":{"line":22,"column":1},"end":{"line":22,"column":1}},"children":[{"type":"text","value":"Note: I’m not an expert in Rust governance, so there are some assumptions made about its model\nbased on my outside perspective. Apologies if I miss any important details about the Rust model,\nbut this is mostly meant as as inspiration, not a report on Rust’s governance :-)","position":{"start":{"line":22,"column":1},"end":{"line":22,"column":1}},"key":"pELX3J0fgq"}],"key":"rFPDFvuIey"}],"key":"EhdfeMZ7OD"},{"type":"heading","depth":2,"position":{"start":{"line":26,"column":1},"end":{"line":26,"column":1}},"children":[{"type":"text","value":"A quick recap of Rust’s governance structure","position":{"start":{"line":26,"column":1},"end":{"line":26,"column":1}},"key":"n8yzBWWKXx"}],"identifier":"a-quick-recap-of-rusts-governance-structure","label":"A quick recap of Rust’s governance structure","html_id":"a-quick-recap-of-rusts-governance-structure","implicit":true,"key":"FLKYHsoZGp"},{"type":"paragraph","position":{"start":{"line":28,"column":1},"end":{"line":29,"column":1}},"children":[{"type":"text","value":"First off, how does Rust govern and organize itself? There are a few few\nkey pieces:","position":{"start":{"line":28,"column":1},"end":{"line":28,"column":1}},"key":"PDd1Iq2yAp"}],"key":"pp9QJJ6mLR"},{"type":"list","ordered":false,"spread":false,"position":{"start":{"line":31,"column":1},"end":{"line":49,"column":1}},"children":[{"type":"listItem","spread":true,"position":{"start":{"line":31,"column":1},"end":{"line":32,"column":1}},"children":[{"type":"text","value":"Any significant changes to the codebase are proposed and discussed with a\n","position":{"start":{"line":31,"column":1},"end":{"line":31,"column":1}},"key":"YQywb8YzXW"},{"type":"link","url":"https://github.com/rust-lang/rfcs","position":{"start":{"line":31,"column":1},"end":{"line":31,"column":1}},"children":[{"type":"text","value":"Request for Comments process","position":{"start":{"line":31,"column":1},"end":{"line":31,"column":1}},"key":"tHAOdiFGbV"}],"urlSource":"https://github.com/rust-lang/rfcs","error":true,"key":"KYdlE1P0dh"},{"type":"text","value":".","position":{"start":{"line":31,"column":1},"end":{"line":31,"column":1}},"key":"XUJFXXYRdF"}],"key":"PcAcLmZT6Q"},{"type":"listItem","spread":true,"position":{"start":{"line":33,"column":1},"end":{"line":35,"column":1}},"children":[{"type":"text","value":"The Rust community is broken down into topic-specific teams. Each has a particular\ndomain over which they make decisions. For a list of several teams, check out\nthe ","position":{"start":{"line":33,"column":1},"end":{"line":33,"column":1}},"key":"wSOjHD5ZZ6"},{"type":"link","url":"https://www.rust-lang.org/governance/","position":{"start":{"line":33,"column":1},"end":{"line":33,"column":1}},"children":[{"type":"text","value":"Rust governance page","position":{"start":{"line":33,"column":1},"end":{"line":33,"column":1}},"key":"CTfevXngI1"}],"urlSource":"https://www.rust-lang.org/governance/","key":"YtJ9YXwEVU"},{"type":"text","value":".","position":{"start":{"line":33,"column":1},"end":{"line":33,"column":1}},"key":"T3BtgH13Du"}],"key":"CwLock7J2l"},{"type":"listItem","spread":true,"position":{"start":{"line":36,"column":1},"end":{"line":37,"column":1}},"children":[{"type":"text","value":"There is also a core-team that cuts across topic teams and has representatives\nfrom each topic team, they discuss project-wide matters (but rarely).","position":{"start":{"line":36,"column":1},"end":{"line":36,"column":1}},"key":"RJJg3uid8J"}],"key":"QotAwJfXc4"},{"type":"listItem","spread":true,"position":{"start":{"line":38,"column":1},"end":{"line":39,"column":1}},"children":[{"type":"text","value":"A new RFC is assigned a team, as well as a “shepherd” from that team. This person’s\njob is to move the RFC process forward, not to comment on or implement the RFC.","position":{"start":{"line":38,"column":1},"end":{"line":38,"column":1}},"key":"xcKv3ofeff"}],"key":"Q2OylFhWEr"},{"type":"listItem","spread":true,"position":{"start":{"line":40,"column":1},"end":{"line":42,"column":1}},"children":[{"type":"text","value":"After a discussion period, all members of the sub-team must vote to enter\na Final Comment Period. This should happen when “enough information is presented in\nthe RFC to make a decision”. It triggers a week-long review window.","position":{"start":{"line":40,"column":1},"end":{"line":40,"column":1}},"key":"DwYTA1aIDO"}],"key":"Yj4xbsjjAN"},{"type":"listItem","spread":true,"position":{"start":{"line":43,"column":1},"end":{"line":45,"column":1}},"children":[{"type":"text","value":"At the end of this window, a decision is made about what to do with the RFC. This\nis made by the members of the sub-team, who (I don’t think) have any strict decision-making\nrules, they can organize themselves in terms of decision-making.","position":{"start":{"line":43,"column":1},"end":{"line":43,"column":1}},"key":"KzuLzG6Cga"}],"key":"qcGYp2YHaK"},{"type":"listItem","spread":true,"position":{"start":{"line":46,"column":1},"end":{"line":49,"column":1}},"children":[{"type":"text","value":"If it is accepted, the RFC becomes “active” which is an invitation for people\nto work on implementing it.","position":{"start":{"line":46,"column":1},"end":{"line":46,"column":1}},"key":"H9MA8Wlwdg"}],"key":"PQcJgwZCkT"}],"key":"msEuiygcbw"},{"type":"heading","depth":2,"position":{"start":{"line":50,"column":1},"end":{"line":50,"column":1}},"children":[{"type":"text","value":"What would this look like in Jupyter?","position":{"start":{"line":50,"column":1},"end":{"line":50,"column":1}},"key":"mdJPlqyEXG"}],"identifier":"what-would-this-look-like-in-jupyter","label":"What would this look like in Jupyter?","html_id":"what-would-this-look-like-in-jupyter","implicit":true,"key":"kDpuot1x2j"},{"type":"paragraph","position":{"start":{"line":52,"column":1},"end":{"line":53,"column":1}},"children":[{"type":"text","value":"Jupyter is a complex and multi-faceted community, but so is Rust, so let’s see\nwhat this decision-making structure would look like in the Jupyter community.","position":{"start":{"line":52,"column":1},"end":{"line":52,"column":1}},"key":"Nr48SiXsKY"}],"key":"I91Ll6uNe1"},{"type":"heading","depth":3,"position":{"start":{"line":55,"column":1},"end":{"line":55,"column":1}},"children":[{"type":"text","value":"General decision-making principles and goals","position":{"start":{"line":55,"column":1},"end":{"line":55,"column":1}},"key":"neOy5ou2qm"}],"identifier":"general-decision-making-principles-and-goals","label":"General decision-making principles and goals","html_id":"general-decision-making-principles-and-goals","implicit":true,"key":"VU7Jn2JvBH"},{"type":"paragraph","position":{"start":{"line":57,"column":1},"end":{"line":58,"column":1}},"children":[{"type":"text","value":"First off, we would adopt many of the same decision-making goals of the RFC\nprocess. Here are a few key ones as I understand it:","position":{"start":{"line":57,"column":1},"end":{"line":57,"column":1}},"key":"wL1tCqSeWn"}],"key":"JVFLtNH5K6"},{"type":"list","ordered":false,"spread":false,"position":{"start":{"line":60,"column":1},"end":{"line":70,"column":1}},"children":[{"type":"listItem","spread":true,"position":{"start":{"line":60,"column":1},"end":{"line":61,"column":1}},"children":[{"type":"text","value":"Be transparent - information about decision-making should be publicly available and\neasy to discover at any moment in time.","position":{"start":{"line":60,"column":1},"end":{"line":60,"column":1}},"key":"YNLIy2EmJs"}],"key":"b558gjie1m"},{"type":"listItem","spread":true,"position":{"start":{"line":62,"column":1},"end":{"line":63,"column":1}},"children":[{"type":"text","value":"Be inclusive - decision-making should strive to include many diverse voices in\nthe conversation.","position":{"start":{"line":62,"column":1},"end":{"line":62,"column":1}},"key":"qTpbRluuZm"}],"key":"JJjcJucQgw"},{"type":"listItem","spread":true,"position":{"start":{"line":64,"column":1},"end":{"line":65,"column":1}},"children":[{"type":"text","value":"Be informative - the goal of the RFC process is to surface relevant information\nand perspectives for making a decision.","position":{"start":{"line":64,"column":1},"end":{"line":64,"column":1}},"key":"uSkuzcIfPc"}],"key":"wPv8m6Cye9"},{"type":"listItem","spread":true,"position":{"start":{"line":66,"column":1},"end":{"line":67,"column":1}},"children":[{"type":"text","value":"Be productive - the goal of the RFC process is to move ideas forward in the community.\nIt should achieve a net-positive in “energy spent” vs. “generated value to the community”.","position":{"start":{"line":66,"column":1},"end":{"line":66,"column":1}},"key":"egXT9JSLyL"}],"key":"llrM6EnxRS"},{"type":"listItem","spread":true,"position":{"start":{"line":68,"column":1},"end":{"line":70,"column":1}},"children":[{"type":"text","value":"Be impactful - don’t use RFCs to bike-shed minor details, or implementation details for a PR.\nThey should be used for significant changes in a repository that require discussion at a high level.","position":{"start":{"line":68,"column":1},"end":{"line":68,"column":1}},"key":"PNNkHGnBZI"}],"key":"hn8NKMGasj"}],"key":"p8Wt5JUSjh"},{"type":"heading","depth":3,"position":{"start":{"line":71,"column":1},"end":{"line":71,"column":1}},"children":[{"type":"text","value":"An RFC in the Jupyter Community","position":{"start":{"line":71,"column":1},"end":{"line":71,"column":1}},"key":"HJvYyPSLqK"}],"identifier":"an-rfc-in-the-jupyter-community","label":"An RFC in the Jupyter Community","html_id":"an-rfc-in-the-jupyter-community","implicit":true,"key":"YG6g6L1Ee5"},{"type":"paragraph","position":{"start":{"line":73,"column":1},"end":{"line":74,"column":1}},"children":[{"type":"text","value":"First off, the mechanism for proposing, iterating on, and making decisions. In\nRust this is an RFC. in Jupyter, such a mechanism has already been proposed!","position":{"start":{"line":73,"column":1},"end":{"line":73,"column":1}},"key":"XmHDasO0gJ"}],"key":"LB4RSjpEzr"},{"type":"paragraph","position":{"start":{"line":76,"column":1},"end":{"line":79,"column":1}},"children":[{"type":"text","value":"The ","position":{"start":{"line":76,"column":1},"end":{"line":76,"column":1}},"key":"ya1nWJ74Oz"},{"type":"link","url":"https://github.com/jupyter/enhancement-proposals","position":{"start":{"line":76,"column":1},"end":{"line":76,"column":1}},"children":[{"type":"text","value":"Jupyter Enhancement Proposals","position":{"start":{"line":76,"column":1},"end":{"line":76,"column":1}},"key":"K4u55Ru4S5"}],"urlSource":"https://github.com/jupyter/enhancement-proposals","error":true,"key":"bHy0GrGeSz"},{"type":"text","value":"\nhave been around for quite some time, though have never been codified into law official\ndecision-making and have become a bit stale. I suspect this is partially because it’s\nunclear what kind of “power” the JEP process has.","position":{"start":{"line":76,"column":1},"end":{"line":76,"column":1}},"key":"QN92Z7isB9"}],"key":"mECa0Jxeow"},{"type":"paragraph","position":{"start":{"line":81,"column":1},"end":{"line":85,"column":1}},"children":[{"type":"text","value":"Recently, ","position":{"start":{"line":81,"column":1},"end":{"line":81,"column":1}},"key":"Wfa8qbC3q4"},{"type":"link","url":"https://github.com/captainsafia","position":{"start":{"line":81,"column":1},"end":{"line":81,"column":1}},"children":[{"type":"text","value":"Safia","position":{"start":{"line":81,"column":1},"end":{"line":81,"column":1}},"key":"WqzwpimVui"}],"urlSource":"https://github.com/captainsafia","error":true,"key":"OTx41RERWw"},{"type":"text","value":" kick-started a process to\n","position":{"start":{"line":81,"column":1},"end":{"line":81,"column":1}},"key":"mBRZ3CJF0y"},{"type":"link","url":"https://github.com/jupyter/enhancement-proposals/pull/29","position":{"start":{"line":81,"column":1},"end":{"line":81,"column":1}},"children":[{"type":"text","value":"revitalize the JEP process","position":{"start":{"line":81,"column":1},"end":{"line":81,"column":1}},"key":"zaqFURh2Po"}],"urlSource":"https://github.com/jupyter/enhancement-proposals/pull/29","data":{"kind":"issue","org":"jupyter","repo":"enhancement-proposals","issue_number":"29"},"internal":false,"protocol":"github","key":"TUTjzoczBN"},{"type":"text","value":", and\nthe proposed process is quite close to what the Rust community uses. I generally think\nthat this PR is a huge improvement, though for the sake of this thought experiment, I’m\njust going to directly port over my understanding of Rust into this blog post.","position":{"start":{"line":81,"column":1},"end":{"line":81,"column":1}},"key":"qWEbGHMziy"}],"key":"UGPazLPNNy"},{"type":"paragraph","position":{"start":{"line":87,"column":1},"end":{"line":88,"column":1}},"children":[{"type":"text","value":"Here’s how a Rust-like process could work in Jupyter. Since already have JEPs, I’ll\nreplace “RFC” with “JEP”.","position":{"start":{"line":87,"column":1},"end":{"line":87,"column":1}},"key":"scq9oVfxHW"}],"key":"wCKVqwo82N"},{"type":"list","ordered":false,"spread":false,"position":{"start":{"line":90,"column":1},"end":{"line":109,"column":1}},"children":[{"type":"listItem","spread":true,"position":{"start":{"line":90,"column":1},"end":{"line":90,"column":1}},"children":[{"type":"text","value":"We have a single “enhancement-proposals” repository where JEP discussion happens","position":{"start":{"line":90,"column":1},"end":{"line":90,"column":1}},"key":"D4CYpXZiav"}],"key":"cpDbD4Rw49"},{"type":"listItem","spread":true,"position":{"start":{"line":91,"column":1},"end":{"line":91,"column":1}},"children":[{"type":"text","value":"This repository has a template for new JEPs help people get started.","position":{"start":{"line":91,"column":1},"end":{"line":91,"column":1}},"key":"ruVEE33FgS"}],"key":"skMAHFfAjd"},{"type":"listItem","spread":true,"position":{"start":{"line":92,"column":1},"end":{"line":94,"column":1}},"children":[{"type":"text","value":"New JEPs begin with general conversations in the community. People get informal\nbuy-in and feedback through discussing in the ","position":{"start":{"line":92,"column":1},"end":{"line":92,"column":1}},"key":"mM972aBUTw"},{"type":"link","url":"https://discourse.jupyter.org","position":{"start":{"line":92,"column":1},"end":{"line":92,"column":1}},"children":[{"type":"text","value":"community forum","position":{"start":{"line":92,"column":1},"end":{"line":92,"column":1}},"key":"sWq0KpQhSR"}],"urlSource":"https://discourse.jupyter.org","key":"YIo2qvt8vy"},{"type":"text","value":"\nor in GitHub repositories.","position":{"start":{"line":92,"column":1},"end":{"line":92,"column":1}},"key":"Pji0Eelik7"}],"key":"ocMJqS4PY8"},{"type":"listItem","spread":true,"position":{"start":{"line":95,"column":1},"end":{"line":96,"column":1}},"children":[{"type":"text","value":"If a person wants to make their JEP “official”, they fill in the JEP template and\nmake a pull-request to the repository.","position":{"start":{"line":95,"column":1},"end":{"line":95,"column":1}},"key":"TfJm9MoAya"}],"key":"QIL1c1zK0y"},{"type":"listItem","spread":true,"position":{"start":{"line":97,"column":1},"end":{"line":97,"column":1}},"children":[{"type":"text","value":"After an initial overview, a Jupyter team is assigned to the JEP.","position":{"start":{"line":97,"column":1},"end":{"line":97,"column":1}},"key":"jASU6m7Ocw"}],"key":"anTyVPhL38"},{"type":"listItem","spread":true,"position":{"start":{"line":98,"column":1},"end":{"line":98,"column":1}},"children":[{"type":"text","value":"That team then picks a shepherd (how the teams do this is up to them).","position":{"start":{"line":98,"column":1},"end":{"line":98,"column":1}},"key":"zm9Bg7hqr7"}],"key":"XMt17lbfkS"},{"type":"listItem","spread":true,"position":{"start":{"line":99,"column":1},"end":{"line":100,"column":1}},"children":[{"type":"text","value":"The shepherd oversees a process of feedback, asks for input from others in the\ncommunity, and directs attention to the JEP on the listservs, community forum, etc.","position":{"start":{"line":99,"column":1},"end":{"line":99,"column":1}},"key":"qonfD3SmWY"}],"key":"uPBoAp34P3"},{"type":"listItem","spread":true,"position":{"start":{"line":101,"column":1},"end":{"line":103,"column":1}},"children":[{"type":"text","value":"When the shepherd thinks that the JEP is ready for a decision, they ask their\nteam to vote on whether it should enter a “final review” phase. No more modifications\nshould be made to the JEP at this point.","position":{"start":{"line":101,"column":1},"end":{"line":101,"column":1}},"key":"zVtE4zNuyW"}],"key":"yu2GwVonh0"},{"type":"listItem","spread":true,"position":{"start":{"line":104,"column":1},"end":{"line":106,"column":1}},"children":[{"type":"text","value":"This triggers a 7-day window for team members to review the JEP. At the\nend of the 7 days, the team votes (say, by a lazy consensus with 50% quorum)\non whether to accept the JEP.","position":{"start":{"line":104,"column":1},"end":{"line":104,"column":1}},"key":"OQfr1QHOMB"}],"key":"Ho7475auJx"},{"type":"listItem","spread":true,"position":{"start":{"line":107,"column":1},"end":{"line":109,"column":1}},"children":[{"type":"text","value":"If accepted, the JEP enters an “active” state and pull-requests are welcome to\nimplement it.","position":{"start":{"line":107,"column":1},"end":{"line":107,"column":1}},"key":"t3W5tuqtlW"}],"key":"LzTGZaPQ65"}],"key":"xm8OHLTiBW"},{"type":"heading","depth":3,"position":{"start":{"line":110,"column":1},"end":{"line":110,"column":1}},"children":[{"type":"text","value":"The teams and peronnel needed to manage this process","position":{"start":{"line":110,"column":1},"end":{"line":110,"column":1}},"key":"M1mBoMA5ps"}],"identifier":"the-teams-and-peronnel-needed-to-manage-this-process","label":"The teams and peronnel needed to manage this process","html_id":"the-teams-and-peronnel-needed-to-manage-this-process","implicit":true,"key":"WmFn7y3ew3"},{"type":"paragraph","position":{"start":{"line":112,"column":1},"end":{"line":117,"column":1}},"children":[{"type":"text","value":"The JEP process is the ","position":{"start":{"line":112,"column":1},"end":{"line":112,"column":1}},"key":"bFDYKWtcFZ"},{"type":"emphasis","position":{"start":{"line":112,"column":1},"end":{"line":112,"column":1}},"children":[{"type":"text","value":"mechanism","position":{"start":{"line":112,"column":1},"end":{"line":112,"column":1}},"key":"uru5X9ZCK0"}],"key":"btkxR0xsPd"},{"type":"text","value":" by which decisions get made, but what\nare the groups that oversee this mechanism? In the Rust community,\nthese teams are broken down by either technical or community topics\n(e.g., “compilers”, “community”, or “packaging”). The Jupyter community\nsimilarly has several focus-groups that touch different parts of the\ninteractive computing stack. Here are a few core ones that basically already exist:","position":{"start":{"line":112,"column":1},"end":{"line":112,"column":1}},"key":"GPfu6mvmw5"}],"key":"jFSkZXOw08"},{"type":"list","ordered":false,"spread":false,"position":{"start":{"line":119,"column":1},"end":{"line":124,"column":1}},"children":[{"type":"listItem","spread":true,"position":{"start":{"line":119,"column":1},"end":{"line":119,"column":1}},"children":[{"type":"strong","position":{"start":{"line":119,"column":1},"end":{"line":119,"column":1}},"children":[{"type":"text","value":"JupyterLab core","position":{"start":{"line":119,"column":1},"end":{"line":119,"column":1}},"key":"hIYF3fROkS"}],"key":"Rz17gAlNA5"}],"key":"BkqWeNazVa"},{"type":"listItem","spread":true,"position":{"start":{"line":120,"column":1},"end":{"line":120,"column":1}},"children":[{"type":"strong","position":{"start":{"line":120,"column":1},"end":{"line":120,"column":1}},"children":[{"type":"text","value":"JupyterHub core","position":{"start":{"line":120,"column":1},"end":{"line":120,"column":1}},"key":"JLsDJN1IbN"}],"key":"xkmifhVxwK"}],"key":"HI4xCQ6G4x"},{"type":"listItem","spread":true,"position":{"start":{"line":121,"column":1},"end":{"line":121,"column":1}},"children":[{"type":"strong","position":{"start":{"line":121,"column":1},"end":{"line":121,"column":1}},"children":[{"type":"text","value":"Infrastructure","position":{"start":{"line":121,"column":1},"end":{"line":121,"column":1}},"key":"FFuJAAyWAE"}],"key":"py7uw0LfoL"}],"key":"gAaVKEaeAH"},{"type":"listItem","spread":true,"position":{"start":{"line":122,"column":1},"end":{"line":122,"column":1}},"children":[{"type":"strong","position":{"start":{"line":122,"column":1},"end":{"line":122,"column":1}},"children":[{"type":"text","value":"Community","position":{"start":{"line":122,"column":1},"end":{"line":122,"column":1}},"key":"hOVUYdXFEV"}],"key":"qJUl78yzef"}],"key":"INl1oFBsBd"},{"type":"listItem","spread":true,"position":{"start":{"line":123,"column":1},"end":{"line":124,"column":1}},"children":[{"type":"strong","position":{"start":{"line":123,"column":1},"end":{"line":123,"column":1}},"children":[{"type":"text","value":"Events","position":{"start":{"line":123,"column":1},"end":{"line":123,"column":1}},"key":"zWjlk4vLJo"}],"key":"LY0yTtLVA3"}],"key":"j7NJ8nSEll"}],"key":"oFUxL9Dv48"},{"type":"paragraph","position":{"start":{"line":125,"column":1},"end":{"line":130,"column":1}},"children":[{"type":"text","value":"One could imagine beginning with this subset of teams, and adding others organically\nover time. Each of the teams listed above would manage JEP processes for their respective\ndomain. They would be given a list of repositories (and maybe a GitHub organization)\nto oversee, and when a new JEP came in, one of the the team members would be\nchosen to shepherd the process. The team would be the definitive source of\ndecision-making for topics in that domain.","position":{"start":{"line":125,"column":1},"end":{"line":125,"column":1}},"key":"H0rclY898W"}],"key":"ttTZ2lzNyZ"},{"type":"paragraph","position":{"start":{"line":132,"column":1},"end":{"line":133,"column":1}},"children":[{"type":"text","value":"Here are a few others that come to mind - they’re a bit less well-defined and might\nbe good candidates for team growth in the future.","position":{"start":{"line":132,"column":1},"end":{"line":132,"column":1}},"key":"nIuPg5WSn7"}],"key":"MeLmjldIwh"},{"type":"list","ordered":false,"spread":false,"position":{"start":{"line":135,"column":1},"end":{"line":143,"column":1}},"children":[{"type":"listItem","spread":true,"position":{"start":{"line":135,"column":1},"end":{"line":135,"column":1}},"children":[{"type":"strong","position":{"start":{"line":135,"column":1},"end":{"line":135,"column":1}},"children":[{"type":"text","value":"The notebook specification","position":{"start":{"line":135,"column":1},"end":{"line":135,"column":1}},"key":"bIE1SIBdpJ"}],"key":"smmC0kiAeN"}],"key":"gTJ4MXfOCv"},{"type":"listItem","spread":true,"position":{"start":{"line":136,"column":1},"end":{"line":136,"column":1}},"children":[{"type":"strong","position":{"start":{"line":136,"column":1},"end":{"line":136,"column":1}},"children":[{"type":"text","value":"Kernels and communication protocols","position":{"start":{"line":136,"column":1},"end":{"line":136,"column":1}},"key":"dWKpNPCv6D"}],"key":"Mj3sH8kBXZ"}],"key":"bHaDF4d4d8"},{"type":"listItem","spread":true,"position":{"start":{"line":137,"column":1},"end":{"line":137,"column":1}},"children":[{"type":"strong","position":{"start":{"line":137,"column":1},"end":{"line":137,"column":1}},"children":[{"type":"text","value":"Visualizations and widgets","position":{"start":{"line":137,"column":1},"end":{"line":137,"column":1}},"key":"YZNM9xpO9M"}],"key":"i93zXj2T6T"}],"key":"JPmfjFldZ3"},{"type":"listItem","spread":true,"position":{"start":{"line":138,"column":1},"end":{"line":138,"column":1}},"children":[{"type":"strong","position":{"start":{"line":138,"column":1},"end":{"line":138,"column":1}},"children":[{"type":"text","value":"Publishing and document formats","position":{"start":{"line":138,"column":1},"end":{"line":138,"column":1}},"key":"mtOrTmwuGl"}],"key":"TaR5hMUDq1"}],"key":"i156p7CY21"},{"type":"listItem","spread":true,"position":{"start":{"line":139,"column":1},"end":{"line":139,"column":1}},"children":[{"type":"strong","position":{"start":{"line":139,"column":1},"end":{"line":139,"column":1}},"children":[{"type":"text","value":"Data specifications","position":{"start":{"line":139,"column":1},"end":{"line":139,"column":1}},"key":"BQ9KrLkeqz"}],"key":"cJYet8S0R6"}],"key":"mfH2WHKVLo"},{"type":"listItem","spread":true,"position":{"start":{"line":140,"column":1},"end":{"line":140,"column":1}},"children":[{"type":"strong","position":{"start":{"line":140,"column":1},"end":{"line":140,"column":1}},"children":[{"type":"text","value":"Finance and accounting","position":{"start":{"line":140,"column":1},"end":{"line":140,"column":1}},"key":"QUvQrOA2cZ"}],"key":"jp5BSf0s7l"}],"key":"NxaI0edF4u"},{"type":"listItem","spread":true,"position":{"start":{"line":141,"column":1},"end":{"line":141,"column":1}},"children":[{"type":"strong","position":{"start":{"line":141,"column":1},"end":{"line":141,"column":1}},"children":[{"type":"text","value":"Technical accessibility","position":{"start":{"line":141,"column":1},"end":{"line":141,"column":1}},"key":"epZM78Zett"}],"key":"Kgm0cF1HTO"}],"key":"yujDlldpAv"},{"type":"listItem","spread":true,"position":{"start":{"line":142,"column":1},"end":{"line":143,"column":1}},"children":[{"type":"strong","position":{"start":{"line":142,"column":1},"end":{"line":142,"column":1}},"children":[{"type":"text","value":"Documentation","position":{"start":{"line":142,"column":1},"end":{"line":142,"column":1}},"key":"UFcrJ4XAq0"}],"key":"fMN3neNmQS"}],"key":"JELKXayTLi"}],"key":"f8zDU5HFQS"},{"type":"paragraph","position":{"start":{"line":144,"column":1},"end":{"line":144,"column":1}},"children":[{"type":"text","value":"There are a few other roles that would need to be created to facilitate this process:","position":{"start":{"line":144,"column":1},"end":{"line":144,"column":1}},"key":"swVlOvhK1S"}],"key":"kRcaRSk6DQ"},{"type":"list","ordered":false,"spread":false,"position":{"start":{"line":146,"column":1},"end":{"line":156,"column":1}},"children":[{"type":"listItem","spread":true,"position":{"start":{"line":146,"column":1},"end":{"line":149,"column":1}},"children":[{"type":"strong","position":{"start":{"line":146,"column":1},"end":{"line":146,"column":1}},"children":[{"type":"text","value":"A JEP communicator","position":{"start":{"line":146,"column":1},"end":{"line":146,"column":1}},"key":"hA4bkBbnyA"}],"key":"FNRfUJ3BUx"},{"type":"text","value":" - someone would need to manage the JEP infrastructure and process\nat a generic level. This doesn’t mean getting involved in individual JEPs, but making sure\nthe process as a whole is functioning, and potentially managing infrastructure around it\n(for example, maintaining a website that lists currently-active JEPs).","position":{"start":{"line":146,"column":1},"end":{"line":146,"column":1}},"key":"FGxlBgK2AL"}],"key":"yW1tZIuR5x"},{"type":"listItem","spread":true,"position":{"start":{"line":150,"column":1},"end":{"line":152,"column":1}},"children":[{"type":"strong","position":{"start":{"line":150,"column":1},"end":{"line":150,"column":1}},"children":[{"type":"text","value":"A core team","position":{"start":{"line":150,"column":1},"end":{"line":150,"column":1}},"key":"icXZFK7ksn"}],"key":"xa6feiJGCj"},{"type":"text","value":" - would need to be created that cuts across the topic-specific teams.\nThis team would exercise large-scale decisions within the community but generally\nrarely exercise their power. Similar to a BDFL.","position":{"start":{"line":150,"column":1},"end":{"line":150,"column":1}},"key":"cskvnmVa2W"}],"key":"qj8m6eY3D7"},{"type":"listItem","spread":true,"position":{"start":{"line":153,"column":1},"end":{"line":156,"column":1}},"children":[{"type":"strong","position":{"start":{"line":153,"column":1},"end":{"line":153,"column":1}},"children":[{"type":"text","value":"A shepherd role","position":{"start":{"line":153,"column":1},"end":{"line":153,"column":1}},"key":"uozI8z71af"}],"key":"WZr6QXT2uh"},{"type":"text","value":" - we’d need to formalize what a “shepherd” is in the Jupyter community.\nPotentially sub-teams would modify this slightly to fit their own needs.","position":{"start":{"line":153,"column":1},"end":{"line":153,"column":1}},"key":"VSCvE7zoms"}],"key":"jZQCM4XePr"}],"key":"uHdQrKqE1F"},{"type":"heading","depth":2,"position":{"start":{"line":157,"column":1},"end":{"line":157,"column":1}},"children":[{"type":"text","value":"What’s the difference between current Jupyter and JEP Jupyter?","position":{"start":{"line":157,"column":1},"end":{"line":157,"column":1}},"key":"mLJUmuaUSi"}],"identifier":"whats-the-difference-between-current-jupyter-and-jep-jupyter","label":"What’s the difference between current Jupyter and JEP Jupyter?","html_id":"whats-the-difference-between-current-jupyter-and-jep-jupyter","implicit":true,"key":"acJSYeDOa4"},{"type":"paragraph","position":{"start":{"line":159,"column":1},"end":{"line":160,"column":1}},"children":[{"type":"text","value":"Thinking through the above scenario, I don’t see too much distance between\nour current situation and a JEP-like process. We:","position":{"start":{"line":159,"column":1},"end":{"line":159,"column":1}},"key":"wXBah0ETqp"}],"key":"UvGbn0ydAN"},{"type":"list","ordered":false,"spread":false,"position":{"start":{"line":162,"column":1},"end":{"line":166,"column":1}},"children":[{"type":"listItem","spread":true,"position":{"start":{"line":162,"column":1},"end":{"line":163,"column":1}},"children":[{"type":"text","value":"Already have ","position":{"start":{"line":162,"column":1},"end":{"line":162,"column":1}},"key":"LwaITG3guz"},{"type":"emphasis","position":{"start":{"line":162,"column":1},"end":{"line":162,"column":1}},"children":[{"type":"text","value":"informal","position":{"start":{"line":162,"column":1},"end":{"line":162,"column":1}},"key":"dU8ePb4RJR"}],"key":"hlWFpWs8Js"},{"type":"text","value":" topic groups, in the form of GitHub organizations,\nforum channels, and meetings (e.g. JupyterLab and JupyterHub come to mind).","position":{"start":{"line":162,"column":1},"end":{"line":162,"column":1}},"key":"g4yL0LvQx7"}],"key":"CJzj2ooBE8"},{"type":"listItem","spread":true,"position":{"start":{"line":164,"column":1},"end":{"line":164,"column":1}},"children":[{"type":"text","value":"Already have a JEP repository with some past proposals in it.","position":{"start":{"line":164,"column":1},"end":{"line":164,"column":1}},"key":"VZ2GhLgDjl"}],"key":"d4hDvusAGp"},{"type":"listItem","spread":true,"position":{"start":{"line":165,"column":1},"end":{"line":166,"column":1}},"children":[{"type":"text","value":"Already have the skeleton of a modernized JEP process thanks to Safia’s awesome work.","position":{"start":{"line":165,"column":1},"end":{"line":165,"column":1}},"key":"k30VfLI3yI"}],"key":"lDlrCcOfYL"}],"key":"CiIWVNthVN"},{"type":"paragraph","position":{"start":{"line":167,"column":1},"end":{"line":167,"column":1}},"children":[{"type":"text","value":"What we’d need to do:","position":{"start":{"line":167,"column":1},"end":{"line":167,"column":1}},"key":"gATmU6u0vU"}],"key":"BX6VkmGoVv"},{"type":"list","ordered":false,"spread":false,"position":{"start":{"line":169,"column":1},"end":{"line":176,"column":1}},"children":[{"type":"listItem","spread":true,"position":{"start":{"line":169,"column":1},"end":{"line":169,"column":1}},"children":[{"type":"text","value":"more officially codify the JEP process","position":{"start":{"line":169,"column":1},"end":{"line":169,"column":1}},"key":"VOqhDVbMD2"}],"key":"hpVanTUTOW"},{"type":"listItem","spread":true,"position":{"start":{"line":170,"column":1},"end":{"line":170,"column":1}},"children":[{"type":"text","value":"make some topic-based teams official, and get people to accept roles on those teams","position":{"start":{"line":170,"column":1},"end":{"line":170,"column":1}},"key":"luh3txPq9w"}],"key":"sArELn28dw"},{"type":"listItem","spread":true,"position":{"start":{"line":171,"column":1},"end":{"line":172,"column":1}},"children":[{"type":"text","value":"build some infrastructure to support the JEP process (e.g. a website to make them searchable\nand discoverable)","position":{"start":{"line":171,"column":1},"end":{"line":171,"column":1}},"key":"wHCpqY0SAn"}],"key":"goL0zarYZl"},{"type":"listItem","spread":true,"position":{"start":{"line":173,"column":1},"end":{"line":176,"column":1}},"children":[{"type":"text","value":"re-work team processes to encourage them to follow the JEP process over time (I suspect this would\nbe the hardest thing to do)","position":{"start":{"line":173,"column":1},"end":{"line":173,"column":1}},"key":"Bm7bJCf21G"}],"key":"h2O8iIxkFl"}],"key":"BQZQwPnSiE"},{"type":"heading","depth":2,"position":{"start":{"line":177,"column":1},"end":{"line":177,"column":1}},"children":[{"type":"text","value":"What’s the difference between Jupyter and Rust?","position":{"start":{"line":177,"column":1},"end":{"line":177,"column":1}},"key":"dlWaQMK5iH"}],"identifier":"whats-the-difference-between-jupyter-and-rust","label":"What’s the difference between Jupyter and Rust?","html_id":"whats-the-difference-between-jupyter-and-rust","implicit":true,"key":"s7PLbqUtOA"},{"type":"paragraph","position":{"start":{"line":179,"column":1},"end":{"line":181,"column":1}},"children":[{"type":"text","value":"Finally, while it’s interesting to port one community’s governance model directly onto another,\nthere are difference between the Jupyter and Rust projects, both technical and social ones.\nHere are a few differences I can think of that might have an impact on how this model would work.","position":{"start":{"line":179,"column":1},"end":{"line":179,"column":1}},"key":"UTtTAFJ0tc"}],"key":"Fd7UwxCNKm"},{"type":"list","ordered":false,"spread":false,"position":{"start":{"line":183,"column":1},"end":{"line":196,"column":1}},"children":[{"type":"listItem","spread":true,"position":{"start":{"line":183,"column":1},"end":{"line":187,"column":1}},"children":[{"type":"strong","position":{"start":{"line":183,"column":1},"end":{"line":183,"column":1}},"children":[{"type":"text","value":"Jupyter evolves fairly quickly","position":{"start":{"line":183,"column":1},"end":{"line":183,"column":1}},"key":"dXNrdLFFG0"}],"key":"A7Otn4t602"},{"type":"text","value":" - Whether it is JupyterLab development, the growth of new\nprotocols or deployments in the JupyterHub stack, or extensions of Jupyter tools for new\nuse-cases, Jupyter seems to move fairly quickly. The RFC (or JEP) model is one that intentionally\nslows things down, so perhaps we’d need to be more picky about when to follow such a model\nvs. when to allow codebases to grow more quickly.","position":{"start":{"line":183,"column":1},"end":{"line":183,"column":1}},"key":"gZDk7VUgy9"}],"key":"FppYgNxkAy"},{"type":"listItem","spread":true,"position":{"start":{"line":188,"column":1},"end":{"line":191,"column":1}},"children":[{"type":"strong","position":{"start":{"line":188,"column":1},"end":{"line":188,"column":1}},"children":[{"type":"text","value":"Jupyter doesn’t have a process like this already","position":{"start":{"line":188,"column":1},"end":{"line":188,"column":1}},"key":"FIlN2ES9mT"}],"key":"v0Ry1J7v9p"},{"type":"text","value":" - The recent JEP updates notwithstanding,\nJupyter doesn’t have a culture of following the JEP process already. This makes me think that\nadopting this process would need to be rolled out slowly over time, and in smaller increments\nin order to make sure teams buy-in to the process.","position":{"start":{"line":188,"column":1},"end":{"line":188,"column":1}},"key":"Q2ameR3Vp7"}],"key":"QIbccDYi4G"},{"type":"listItem","spread":true,"position":{"start":{"line":192,"column":1},"end":{"line":196,"column":1}},"children":[{"type":"strong","position":{"start":{"line":192,"column":1},"end":{"line":192,"column":1}},"children":[{"type":"text","value":"Jupyter doesn’t have many official roles/titles","position":{"start":{"line":192,"column":1},"end":{"line":192,"column":1}},"key":"RA1cVblxoF"}],"key":"x5hlb2trbc"},{"type":"text","value":" - Adding extra complexity to governance\nalso adds extra responsibility and labor needed to manage that complexity. In order to\nensure that the work gets done, and credit is given to those doing the work, we’d need to grow\na culture of creating specific roles and responsibility for those roles.","position":{"start":{"line":192,"column":1},"end":{"line":192,"column":1}},"key":"VSknei2YTj"}],"key":"ytuaewFh1d"}],"key":"aFDe4mKjUU"},{"type":"heading","depth":2,"position":{"start":{"line":197,"column":1},"end":{"line":197,"column":1}},"children":[{"type":"text","value":"Wrapping up","position":{"start":{"line":197,"column":1},"end":{"line":197,"column":1}},"key":"b6eeUycJm6"}],"identifier":"wrapping-up","label":"Wrapping up","html_id":"wrapping-up","implicit":true,"key":"BZXmenCaQC"},{"type":"paragraph","position":{"start":{"line":199,"column":1},"end":{"line":201,"column":1}},"children":[{"type":"text","value":"I’m probably missing some things, but this seems like a reasonable plan! As I mentioned\nabove, this post has mostly been a thought-experiment, but if anybody has thoughts on bringing\nthis into the governance refactoring process, I’d be happy to talk more.","position":{"start":{"line":199,"column":1},"end":{"line":199,"column":1}},"key":"s6L6DLUGiI"}],"key":"NN4KK1nTBs"}],"key":"I4vUTdTQK3"}],"key":"vjzfdFnZKn"},"references":{"cite":{"order":[],"data":{}}},"footer":{"navigation":{"prev":{"title":"Automating Jupyter Book deployments with CI/CD","url":"/blog/2019/2019-10-11-automating-jb","group":"2019"},"next":{"title":"Analyzing intracranial electrophysiology data with xarray","url":"/blog/2019/2019-10-22-xarray-neuro","group":"2019"}}},"domain":"http://localhost:3000"}